[
    {
        "User": "Sinais Visões e Profecias 👑☄🌟",
        "Content": "The #Economist\nOs #presidentes não têm de ser #santos e esperamos que um segundo mandato de Donald #Trump evite o desastre. Mas ele representa um risco inaceitável para a #América e para o mundo. Se o The Economist votasse, votaríamos em #Kamala Harris https://t.co/IGPM7rEtDv",
        "Created_at": "Sun Nov 03 15:07:55 +0000 2024"
    },
    {
        "User": "TFB",
        "Content": "@LvKashing VOTE #TRUMP",
        "Created_at": "Sun Nov 03 15:25:43 +0000 2024"
    },
    {
        "User": "Akash",
        "Content": "Ostada reachhh\n\n#shailenzo #sstvi  #Trump #Garime #maynata #HurricanMilton #grandefratello #shavier #tommavi",
        "Created_at": "Sun Nov 03 15:26:01 +0000 2024"
    },
    {
        "User": "Nikhil kella",
        "Content": "Pedro almodovor\n\n#shailenzo #sstvi #Trump #Garime #maynata #HurricanMilton #grandefratello #shaviers #biggbosstamil8",
        "Created_at": "Sun Nov 03 15:30:08 +0000 2024"
    },
    {
        "User": "🇧🇷 VLOGDOLISBOA",
        "Content": "Donald Trump cresce, e Kamala Harris perde força em pesquisas #Trump #Kamala #PlenoNews  https://t.co/j0kU6Y0iRD via @YouTube",
        "Created_at": "Sun Nov 03 15:32:48 +0000 2024"
    },
    {
        "User": "Annarita Briganti",
        "Content": "Povera America.\n#trump \n#KamalaHarris https://t.co/mSMqCl7wR3",
        "Created_at": "Sun Nov 03 15:51:57 +0000 2024"
    },
    {
        "User": "Jornal ES HOJE",
        "Content": "#KamalaHarris  ‼️Veja abaixo alguns dos principais nomes que apoiaram os candidatos à presidência americana👇\n\nhttps://t.co/oceNHqokc0\n\n#Trump #beyonce #jornalcapixaba #jornalonline #taylorswift #billieeilish #50cent #eminim #azealiabanks #melgibson",
        "Created_at": "Sun Nov 03 15:54:19 +0000 2024"
    },
    {
        "User": "SandraSaray",
        "Content": "Vote #Trump\nPela Vida",
        "Created_at": "Sun Nov 03 15:58:40 +0000 2024"
    },
    {
        "User": "Mídia Livre",
        "Content": "Kamala Harris falhou em proteger a fronteira, permitindo que criminosos cruzassem e ameaçassem a vida de americanos. Com sua liderança, a segurança nacional está em risco e nada muda. @realDonaldTrump #TrumpVance2024 #MAGA #Trump @elonmusk https://t.co/P5sv7kk0iB",
        "Created_at": "Sun Nov 03 16:04:32 +0000 2024"
    },
    {
        "User": "gomes",
        "Content": "mataram a porra do esquilo atoa #esquilo #trump",
        "Created_at": "Sun Nov 03 16:04:46 +0000 2024"
    },
    {
        "User": "DataProf ⚜️",
        "Content": "@IvankaNews_ Vote #Trump ?",
        "Created_at": "Sun Nov 03 16:12:37 +0000 2024"
    },
    {
        "User": "Words & More - parole e altro!",
        "Content": "#3novembre oltre #GrandeFratello #XF2024 #TEMPTATIONISLAND #AMICI24 #BallandoConLeStelle #UdineseJuve #tvtalk #McLaren #Trump #Piastri #Norris #Thuram #jvtblive #MonzaMilan #tusiquevales #Leao #BrazilGP #DomenicaIn compagnia di #uominiedonne che amano https://t.co/mcuaOmPA75 https://t.co/16KNdfiFkx",
        "Created_at": "Sun Nov 03 16:15:00 +0000 2024"
    }
]