[
    {
        "User": "lucas",
        "Content": "eu chegando semana que vem em xique xique pra votar na kamala https://t.co/raBQ0UcZWt",
        "Created_at": "Mon Nov 04 03:15:35 +0000 2024"
    },
    {
        "User": "Adriano",
        "Content": "Bidem e Kamala) Lula e Trump( Bolsonaro)?",
        "Created_at": "Mon Nov 04 03:15:49 +0000 2024"
    },
    {
        "User": "Emerson Esteves",
        "Content": "@renatajbarreto Se o Trump ganhar pelo menos o mundo todo saberá quem governa lá, hoje não sabemos. E se a Kamala ganhar continuaremos sem saber, ela é tipo uma Dilma, só que sem o Lula.",
        "Created_at": "Mon Nov 04 03:15:51 +0000 2024"
    },
    {
        "User": "Alfinetados do Dia",
        "Content": "🚨AGORA: O ex-presidente Jair Bolsonaro declarou apoio à Donald Trump nas eleições presidenciais dos Estados Unidos contra Kamala Harris. https://t.co/sgr3ju3AC6",
        "Created_at": "Mon Nov 04 03:16:02 +0000 2024"
    },
    {
        "User": "Phil",
        "Content": "Eu ate nem sou muito fã do Trump, mas só de ver o tanto de bostas esquerdistas que torcem pela Kamala, eu até quero ver ele ganhar.",
        "Created_at": "Mon Nov 04 03:16:30 +0000 2024"
    },
    {
        "User": "CNN Brasil",
        "Content": "O analista de Internacional Lourival Sant’Anna mostra o caminho que os candidato à Casa Branca Kamala Harris e Donald Trump precisam fazer para obter os 270 delegados no colégio eleitoral dos Estados Unidos #CNNBrasil https://t.co/1qRR8xxgwY",
        "Created_at": "Mon Nov 04 03:16:52 +0000 2024"
    },
    {
        "User": "CidadaoParticipativoBR",
        "Content": "@NewsLiberdade tanto Trump, quanto Kamala não favorecem em nada o Brasil em particular.",
        "Created_at": "Mon Nov 04 03:17:32 +0000 2024"
    },
    {
        "User": "🇧🇷JENIFER COSTA🇧🇷",
        "Content": "📌🇺🇸 “Donald Trump encerra oficialmente sua campanha eleitoral em comício na Geórgia com vantagem sobre a esquerdista Kamala Harris.\n#TrumpVance2024\n#MAGA2024 https://t.co/mFPBOKRQrZ",
        "Created_at": "Mon Nov 04 03:17:44 +0000 2024"
    },
    {
        "User": "Elon … Silva🇧🇷",
        "Content": "Estranho hein: CNN denuncia que Kamala Harris está vinculando anúncios pró-Israel na Pensilvânia e pró-Palestina no Michigan\n https://t.co/r7KMAxzgdP",
        "Created_at": "Mon Nov 04 03:18:01 +0000 2024"
    },
    {
        "User": "Libertário 013",
        "Content": "@yasminancap Não existem?\nTem milhões deles por lá. Todos foram para swing states para votarem pra Kamala.\nE não, eles não fogem do socialismo. Eles fogem do socialismo que não deu certo pra um que ainda não deu tão errado.\nEssas pessoas são socialistas. Elas votam em socialistas por isso.",
        "Created_at": "Mon Nov 04 03:18:19 +0000 2024"
    },
    {
        "User": "Natan",
        "Content": "@vermelhos_sim Torço pela kamala, só ora dar guerra civil e morrer geral.",
        "Created_at": "Mon Nov 04 03:18:51 +0000 2024"
    },
    {
        "User": "Lylly Sincera",
        "Content": "@eleicoesempauta Pesquisa Do New York times é uma FRAUDE.  Estão apoiador a Kamala.",
        "Created_at": "Mon Nov 04 03:19:02 +0000 2024"
    },
    {
        "User": "Santiago",
        "Content": "O tema da redação do enem esse ano foi uma homenagem a kamala https://t.co/DtehRYLpSo",
        "Created_at": "Mon Nov 04 03:19:21 +0000 2024"
    },
    {
        "User": "ˢᶜᶜᵖ",
        "Content": "@Giooxd2 mesmo sabendo que é um pior que o outro prefiro a kamala (opinião vinda de xique xique- ba",
        "Created_at": "Mon Nov 04 03:19:51 +0000 2024"
    },
    {
        "User": "Leodecio Tietbohl",
        "Content": "Se Diddy mostrar todos os videos dos escândalos envolvendo celebridades, Donald Trump ja estaria eleito antecipadamente. Por isso a lacrosfera  toda vota Kamala. Mesmo sendo um estado democrata, dá pars entender Arnold Scwhasnneger, republicano, votar em Kamala?",
        "Created_at": "Mon Nov 04 03:19:52 +0000 2024"
    },
    {
        "User": "TANGERINA 🍊",
        "Content": "Os eleitores negros estão com o Donald Trump, não com a Kamala Harris! https://t.co/m9wrXsWdKe",
        "Created_at": "Mon Nov 04 03:20:14 +0000 2024"
    },
    {
        "User": "ALEX*MEDEIROS",
        "Content": "Na cobertura da @CNNBrasil a Kamala Harris já vai tomar posse.",
        "Created_at": "Mon Nov 04 03:20:23 +0000 2024"
    },
    {
        "User": "GREMISTA TRI DA AMÉRICA #GRACIASSUÁREZ",
        "Content": "@anitablian Outro dis ele declarou pra Kamala?",
        "Created_at": "Mon Nov 04 03:20:57 +0000 2024"
    },
    {
        "User": "GustavoMota",
        "Content": "É isso, a vitória já é da Kamala",
        "Created_at": "Mon Nov 04 03:21:38 +0000 2024"
    },
    {
        "User": "kid preto do comando maluco",
        "Content": "Se a Kamala ganhar vai rolar guerra civil",
        "Created_at": "Mon Nov 04 03:21:42 +0000 2024"
    }
]