[
    {
        "User": "mutirão Globo de Ouro Fernanda Torres Best Actress",
        "Content": "mtos homens gostosos por cm quadrado  n consigo dar em cima de todos tá me dando crise de ansiedade",
        "Created_at": "Sun Nov 03 04:13:34 +0000 2024"
    },
    {
        "User": "J.H. Fonseca",
        "Content": "### PESQUISA MORNING CONSULT, UMA DAS MAIS À ESQUERDA, TRAZ KAMALA E TRUMP TECNICAMENTE EMPATADO EM SUA SONDAGEM FINAL.\n\n- Harris: 49% (-1) \n- Trump: 47% (=)\n\nComo eu disse, ninguém sabe p* nenhuma e muitos perderão a reputação. O número acima é compatível com Trump eleito.",
        "Created_at": "Sun Nov 03 04:13:42 +0000 2024"
    },
    {
        "User": "paloma",
        "Content": "não teria ninguém melhor pra fazer a kamala a não ser a maya",
        "Created_at": "Sun Nov 03 04:14:19 +0000 2024"
    },
    {
        "User": "O POLÍMATA TUPINIQUIM",
        "Content": "@ACTBrigitte Kamala Harris tem o apoio de Xi Jinping,Putin, George Soros, Bill Gates, MÍDIA,Astros de Hollywood...DIGA NÃO a comunista, Kamala Harris",
        "Created_at": "Sun Nov 03 04:15:12 +0000 2024"
    },
    {
        "User": "Roger (Pelo fim da escala 6x1)",
        "Content": "@LuisaSeraf29355 @folha E nem fico em rede social defendendo milionário.",
        "Created_at": "Sun Nov 03 04:16:04 +0000 2024"
    },
    {
        "User": "Irônico",
        "Content": "@Xd1Perigoso @DamaDeFerroTV De fato, porém, o argumento do Papa contra Trump é o dito no vídeo. Já o argumento contra Kamala é ela ser pro aborto (assassinato de bebês no ventre).",
        "Created_at": "Sun Nov 03 04:16:37 +0000 2024"
    },
    {
        "User": "lavynia",
        "Content": "AXÉ KAMALA to chegando da viagem de 313 horas de goiânia até pensilvânia pra votar em você irmã",
        "Created_at": "Sun Nov 03 04:16:40 +0000 2024"
    },
    {
        "User": "EzequielSEP1914",
        "Content": "@PKFreitas18 @Zanfa Democratas( kamala) mandou matar o esquilo, povo nos EUA tão revoltados, a história tá viralizando lá em todo canto",
        "Created_at": "Sun Nov 03 04:16:50 +0000 2024"
    },
    {
        "User": "Cassio silva",
        "Content": "@JHdaFonseca Kamala já esta eleita",
        "Created_at": "Sun Nov 03 04:17:19 +0000 2024"
    },
    {
        "User": "Ricardo Goulart Nunes",
        "Content": "@EliseWilshaw São capazes de tudo . Mas só ganha na fraude. Hoje está tendo um evento em Tampa com Kamala e Hilary. Em um lugar pequeno . Não encheu .",
        "Created_at": "Sun Nov 03 04:17:26 +0000 2024"
    },
    {
        "User": "AlwaysPatriot 🇧🇷 🇺🇸 🇮🇱 🇺🇾",
        "Content": "SPACE LIBERDADE \n@NewsLiberdade\n🚨URGENTE - A CNN denuncia que Kamala Harris está vinculando anúncios pró-Israel na Pensilvânia e pró-Palestina no Michigan\n\n“A candidata mais falsa da história na campanha mais falsa da história, zero princípios” https://t.co/sKdtqQaxfi",
        "Created_at": "Sun Nov 03 04:18:25 +0000 2024"
    },
    {
        "User": "Eleeseu",
        "Content": "Lula apoia Kamala , seria anormal se não o fizesse . A direita é tolinha d +.",
        "Created_at": "Sun Nov 03 04:18:53 +0000 2024"
    },
    {
        "User": "Eixo Político",
        "Content": "🇺🇸 Kamala Harris participa do Saturday Night Live a dois dias da eleição americana. https://t.co/VI3mNlSrIy",
        "Created_at": "Sun Nov 03 04:18:56 +0000 2024"
    },
    {
        "User": "MH🔶🐍",
        "Content": "@yasminancap Odds de casa de apostas dificilmente ficam erradas, tá pagando muito apostar na Kamala, seria prejuízo se ela tivesse reais chances.",
        "Created_at": "Sun Nov 03 04:19:20 +0000 2024"
    },
    {
        "User": "Rogeriobeto",
        "Content": "@abelferreira222 @gonca_seu @atlanticista Nunca vi uma analise tão ruim. Parabéns. E Trump ou Kamala não tem nada a ver com  STF do Brasil. Vai rezar pra pneu acara.",
        "Created_at": "Sun Nov 03 04:19:36 +0000 2024"
    },
    {
        "User": "O POLÍMATA TUPINIQUIM",
        "Content": "@ricardors_ofc @FbioMontalvao Kamala Harris é uma versão AMERICANA da ex-presidente do Brasil, Dilma Rousseff. AMBAS, idiotas úteis do Socialismo.",
        "Created_at": "Sun Nov 03 04:19:44 +0000 2024"
    },
    {
        "User": "Charles",
        "Content": "@R38TAO Kamala vai perder mesmo, Renato?",
        "Created_at": "Sun Nov 03 04:19:54 +0000 2024"
    }
]