[
    {
        "User": "Hallyson mata",
        "Content": "@Thiago1321417 @MarceloUchoa_ @EvandroLeitao Tô falando de sentimento. Impressão de quem está de fora. \n\nComo falei domingo já está bem aí.",
        "Created_at": "Tue Oct 22 23:03:21 +0000 2024"
    },
    {
        "User": "SFNchannel 🇸🇩",
        "Content": "@EvandroLeitao Ele mudou sim @EvandroLeitao mudou pra muito pior! Antes ele mostrava o que é, hoje além de ser essa aberração que representa, ele finge que não é, numa tentativa de enganar o povo de Fortaleza.  Um sujeito q diz que é da igreja mas parece agir pela mão do 😈",
        "Created_at": "Tue Oct 22 23:07:31 +0000 2024"
    },
    {
        "User": "Ricardo",
        "Content": "@MarceloUchoa_ @EvandroLeitao É só jogar a carteira de trabalho e veja a mágica acontecer 😂😂😂😂",
        "Created_at": "Tue Oct 22 23:10:20 +0000 2024"
    },
    {
        "User": "FRED Medeiros",
        "Content": "@EvandroLeitao Vergonha nacional é o @LulaOficial ex-presidiario descondenado e jogado na cadeira de presidente depois de pagar alguns bilhões ao STF... ISSO é vergonha....",
        "Created_at": "Tue Oct 22 23:12:43 +0000 2024"
    },
    {
        "User": "Marcelo Miranda",
        "Content": "@MarceloUchoa_ @EvandroLeitao Em Natal do mesmo jeito! Uma onda 13 invade as capitais vizinhas❤️",
        "Created_at": "Tue Oct 22 23:22:25 +0000 2024"
    },
    {
        "User": "Carlos Henrique lima de melo.",
        "Content": "@EvandroLeitao Dá-lhe Evandro Leitão 50.\n\nVamos arrastar está eleição.\n\nE fora o raspa ku .",
        "Created_at": "Tue Oct 22 23:24:15 +0000 2024"
    },
    {
        "User": "Edney Brito",
        "Content": "@EmersonAnomia @EvandroLeitao Estão tudo batendo no André , nesse exato momento a 20:25h do dia 22 ele está com mais de 10 mil eleitores",
        "Created_at": "Tue Oct 22 23:26:08 +0000 2024"
    },
    {
        "User": "Edney Brito",
        "Content": "@EmersonAnomia @EvandroLeitao Não vai caber tanta gente https://t.co/jFNcfIqANN",
        "Created_at": "Tue Oct 22 23:30:04 +0000 2024"
    },
    {
        "User": "Águeda",
        "Content": "@EvandroLeitao FORA: André Fernandes 🤡🤮☝️\nVote CERTO ⚠️⛔⚠️ https://t.co/YAUuNyBTNe",
        "Created_at": "Tue Oct 22 23:32:04 +0000 2024"
    },
    {
        "User": "Fernando Araujo",
        "Content": "@FCCRATEUS @EvandroLeitao Partido NAZIFASCISTA, nem sb a mira de uma arma .",
        "Created_at": "Tue Oct 22 23:33:14 +0000 2024"
    },
    {
        "User": "Denilson Matos",
        "Content": "@tropicaliaviva @GuilhermeBoulos @EvandroLeitao @natbonavides Em São Paulo vou votar no 13.",
        "Created_at": "Tue Oct 22 23:33:15 +0000 2024"
    },
    {
        "User": "Nacameuvingo",
        "Content": "@EvandroLeitao Finalmente batendo na tecla correta, Evandro",
        "Created_at": "Tue Oct 22 23:35:26 +0000 2024"
    },
    {
        "User": "Nelson de oliveira",
        "Content": "@EvandroLeitao Se realmente ele fez tais declarações, não tem a menor condição de dirigir o estado! Chega a ser um caso de burrice!",
        "Created_at": "Tue Oct 22 23:36:29 +0000 2024"
    },
    {
        "User": "Emerson Leite",
        "Content": "@MarceloUchoa_ @EvandroLeitao Vai pra Cuba vermelhão….",
        "Created_at": "Tue Oct 22 23:39:11 +0000 2024"
    },
    {
        "User": "Emerson Leite",
        "Content": "@MarceloUchoa_ @EvandroLeitao Aqui 6 não tem mais espaço, vagabundo…\nHiiiiiiiiiiiiiiiiiiiiiiiiiiiiiiUuuuuuuuuuuuuuuu",
        "Created_at": "Tue Oct 22 23:40:06 +0000 2024"
    },
    {
        "User": "Maria Da Paz e Joao Da Paz",
        "Content": "@MarceloUchoa_ @EvandroLeitao Jogaram a mortadela",
        "Created_at": "Tue Oct 22 23:40:20 +0000 2024"
    }
]