[
    {
        "User": "Keli fbb",
        "Content": "@guimaraes13PT @EvandroLeitao Dinheiro na cueca",
        "Created_at": "Wed Oct 23 22:13:07 +0000 2024"
    },
    {
        "User": "Ana Regina Barbosa",
        "Content": "@MariLacerdaPT @EvandroLeitao A eleição não terminou gente. Vamos trabalhar com humildade e conquistar votos.",
        "Created_at": "Wed Oct 23 22:13:23 +0000 2024"
    },
    {
        "User": "Emerson Leite",
        "Content": "@guimaraes13PT @EvandroLeitao MAIS DINHEIRO PRA CUECA ? Agora deve ser CUECÃO NÉ ? Vagabundo\nDomingo vão se foder…espera só imbecil",
        "Created_at": "Wed Oct 23 22:13:54 +0000 2024"
    },
    {
        "User": "José Guimarães",
        "Content": "Fortaleza está tomada pelo 13 do ⁦@EvandroLeitao⁩ nosso próximo prefeito https://t.co/54ogkciied",
        "Created_at": "Wed Oct 23 22:14:23 +0000 2024"
    },
    {
        "User": "Nicodemos R. Fazuele de Sales",
        "Content": "@EvandroLeitao Vai dar PT",
        "Created_at": "Wed Oct 23 22:14:45 +0000 2024"
    },
    {
        "User": "Leonardo Reis",
        "Content": "No 2o turno é PT de norte a sul.\n\nCuiabá/MT: Lúdio Cabral 1️⃣3️⃣\n\nFortaleza/CE: Evandro Leitão 1️⃣3️⃣\n\nNatal/RN: Natália Bonavides 1️⃣3️⃣\n\nPorto Alegre/RS: Maria do Rosário 1️⃣3️⃣\n\n@ludiocabral \n@EvandroLeitao \n@natbonavides \n@mariadorosario",
        "Created_at": "Wed Oct 23 22:19:50 +0000 2024"
    },
    {
        "User": "WanderValero 🚀",
        "Content": "@EvandroLeitao À esquerda recriou mais uma taxa ( DPVAT ), porém a DIREITA não vai cobrar. https://t.co/PoCXS8BMzm",
        "Created_at": "Wed Oct 23 22:27:17 +0000 2024"
    },
    {
        "User": "FABY ANTIBOZISTA🚩",
        "Content": "@vinicios_betiol O que me choca é ainda ter 35% cogitando votar nesse estrupício! Era pra ser 0%.\nQue tipos de mulheres são essas? \n\n@EvandroLeitao para prefeito de Fortaleza 1️⃣3️⃣\n\n#LulaBrasilForte https://t.co/uZSmd9miOl",
        "Created_at": "Wed Oct 23 22:31:11 +0000 2024"
    },
    {
        "User": "Ergonoce",
        "Content": "@andrearalp @opovo @EvandroLeitao Vcs são que nem mosca ,adoram viver na merda.",
        "Created_at": "Wed Oct 23 22:31:51 +0000 2024"
    },
    {
        "User": "PAULO 101% CEARENSE/NORDESTINO COM ORGULHO",
        "Content": "@Gabriel24795916 @guimaraes13PT @EvandroLeitao Pois é...",
        "Created_at": "Wed Oct 23 22:32:41 +0000 2024"
    },
    {
        "User": "Marcelo Uchôa",
        "Content": "Já, já, 20:15h, estarei na @revistaforum com a @maria_fro conversando sobre as eleições no Brasil. Mais uma oportunidade de pedir pra turma de fora cobrar da parentada aqui q vote no @EvandroLeitao 13 Prefeito. Agradeço se assistir e compartilhar. ✊🚩🚀🚀 https://t.co/m6HP7Zs0dI",
        "Created_at": "Wed Oct 23 22:33:41 +0000 2024"
    },
    {
        "User": "teo klo",
        "Content": "@EvandroLeitao para de mentir",
        "Created_at": "Wed Oct 23 22:34:51 +0000 2024"
    },
    {
        "User": "tamandua tata",
        "Content": "@FCCRATEUS @EvandroLeitao *FATO⬇️\n*Bolsonaro SEMPRE teve Razão!\n&gt;a \"Extrema Esquerda\" INFILTRA, RECORTA e REMONTA imagens...para passar a impressão do Bozo Malvadão...a exemplo qdo ele explicou sobre o \"PROTOCOLO MANDETTA⬇️\"\n&gt;Lembram!\n*ou seja, a esquerda só produz FAKE NEWS\nkkk\nhttps://t.co/FkhXUlSsyc",
        "Created_at": "Wed Oct 23 22:38:10 +0000 2024"
    },
    {
        "User": "Milson Santos",
        "Content": "@IRISPINHEIRA @FCCRATEUS @EvandroLeitao Kakakakk https://t.co/pLaqjRrZmP",
        "Created_at": "Wed Oct 23 22:41:26 +0000 2024"
    }
]