[
    {
        "User": "Kátia Marinho",
        "Content": "@mariadorosario Oi Maria Champinha",
        "Created_at": "Sat Oct 26 17:16:44 +0000 2024"
    },
    {
        "User": "Maria do Rosário",
        "Content": "A saúde é um problema gravíssimo em Porto Alegre. Precisa ser resolvido imediatamente antes que o povo pague mais caro pela irresponsabilidade do prefeito. \n\nA mudança tem nome e trabalha com seriedade, é Maria! Vote 13! ✅\n\n#MariaETamyres #MariaÉ13 #PovonaPrefeitura #PortoAlegre https://t.co/sTbNKrf93W",
        "Created_at": "Sat Oct 26 17:18:22 +0000 2024"
    },
    {
        "User": "Haffner",
        "Content": "@mariadorosario Este incompetente nada fez. Agora a cidade está tomada de obras realizadas de forma precária, sinalização inadequada, materiais de má qualidade e mão de obra desqualificada. Dinheiro público indo para o esgoto.",
        "Created_at": "Sat Oct 26 17:20:39 +0000 2024"
    },
    {
        "User": "Kátia Marinho",
        "Content": "@mariadorosario Votou contra a anistia do RS. Maria Champinha",
        "Created_at": "Sat Oct 26 17:22:12 +0000 2024"
    },
    {
        "User": "Carlão 🇧🇷🇱🇷🇮🇱",
        "Content": "@ai61429 @mariadorosario Vc é a *Solução* para os problemas ? Só se for da Odebrecht sua corrupta\n\nDefende bandido, desde que esteja alinhado com seus pensamentos né \n\nAdora liberdade, mas quer ver a falta dela para comediantes como Danilo Gentili",
        "Created_at": "Sat Oct 26 17:22:52 +0000 2024"
    },
    {
        "User": "Helder Salomão",
        "Content": "Porto Alegre é @mariadorosario 1️⃣3️⃣\n#LulaBrasilForte https://t.co/hRTyMCbrfO",
        "Created_at": "Sat Oct 26 17:27:14 +0000 2024"
    },
    {
        "User": "Maria do Rosário",
        "Content": "Quem roda todo dia pela cidade, quem é motorista de aplicativo, sabe da importância em ter um ponto de apoio, para ir ao banheiro, carregar o celular, esquentar um alimento. \n\n A mudança segura é Maria! Vote 13! Confia! 🌻\n\n#MariaETamyres #MariaÉ13 #PovonaPrefeitura #PortoAlegre https://t.co/pdiQrvbHor",
        "Created_at": "Sat Oct 26 17:30:39 +0000 2024"
    },
    {
        "User": "Alzira Brandão",
        "Content": "@mariadorosario Se a saúde e um problema gravíssimo aí, pq mandaram gente daí  pra assumir gestão no Rio no hospital de bonsucesso?",
        "Created_at": "Sat Oct 26 17:31:34 +0000 2024"
    },
    {
        "User": "Timoteo",
        "Content": "@laurasito @mariadorosario Gaúcho não vota nela,né...",
        "Created_at": "Sat Oct 26 17:32:52 +0000 2024"
    },
    {
        "User": "seco luchese",
        "Content": "Do mesmo partido do @LulaOficial  @mariadorosario  e da @JanjaLula  .",
        "Created_at": "Sat Oct 26 17:32:59 +0000 2024"
    },
    {
        "User": "Sandroka13",
        "Content": "@luizmuller @mariadorosario Melo querendo posar de bom moço ficou acuado o tempo todo, só transferindo a responsabilidade dele pro PT e pro LULA. https://t.co/yFKRLnle4B",
        "Created_at": "Sat Oct 26 17:33:11 +0000 2024"
    },
    {
        "User": "Timoteo",
        "Content": "@bedendo_santo @laurasito @mariadorosario Alguém vota nisso?",
        "Created_at": "Sat Oct 26 17:33:40 +0000 2024"
    },
    {
        "User": "ZÓIO AZUL",
        "Content": "@mariadorosario VOTEM MARIA DO ROSÁRIO https://t.co/haNGqkctrx",
        "Created_at": "Sat Oct 26 17:37:07 +0000 2024"
    },
    {
        "User": "Nilcea De Moura Jardim",
        "Content": "@heldersalomao @mariadorosario Deu livre Porto Alegre dessa desgraça..",
        "Created_at": "Sat Oct 26 17:37:16 +0000 2024"
    },
    {
        "User": "Maria do Rosário",
        "Content": "Inúmeras comunidades em Porto Alegre estão abandonadas. Lixo espalhado, esgoto a céu aberto, descaso. Completamente diferente da propaganda de TV. \n\nNão é essa a Porto Alegre que queremos. Vamos mudar juntos, juntas! Vote 13! \n\n#povonaprefeitura #mariaé13 #portoalegre https://t.co/h14McbFAHX",
        "Created_at": "Sat Oct 26 17:39:59 +0000 2024"
    },
    {
        "User": "Nel 🇧🇷🚩🚩🌵",
        "Content": "@MaluNogueiraPT @Cavalheira @WilmarPetista @InesNasciment12 @PradoEimar @wwanniacbot @prudentemarlene @valfachi @JOSDANIELROCHA3 @AnnaS_Gdottir @Dry_ie @CarlosR28356381 @RogriaFranca1 @nadiaprado7 @MarquesKs @LulistaPetista @AmoraesBah @borgescm @augustotomanov @robeuman @de_borgez @Mairaavelino64 @Ritss65 @joanaouteresa @bethonira @andr67272991 @Db1Dutra @carlosrafer @IvoneideBa9705 @ADTur_Tur @marineslazzaron @RosineiRodrig16 @Paulo_CD_ @Liz6macielgmai1 @VillasEstther @MegGestaoDiels @PetistaAlerta @neylopesmachado @noma1960ju16560 @FioravanteFern9 @mariaceliaoli13 @SolSantos173697 @marinesssilva @MnicaAp2691375 @analiseagora @BelleBelle_VAL @binha1954 @Mano1Ju @mariadorosario Boa tarde amiga Malu, bom sábado!\n#LulaEstamosComVoce https://t.co/bCPa9oTEKw",
        "Created_at": "Sat Oct 26 17:40:28 +0000 2024"
    },
    {
        "User": "Saio Nunes",
        "Content": "Porto Alegre, Domingo dia 27/10  #Vote13 em @mariadorosario, mulher guerreira! ❤️❤️\n#LulaBrasilForte❤️",
        "Created_at": "Sat Oct 26 17:41:29 +0000 2024"
    },
    {
        "User": "Saio Nunes",
        "Content": "Porto Alegre, Domingo dia 27/10  #Vote13 em @mariadorosario, mulher guerreira! ❤️❤️\n#LulaBrasilForte❤️\nCOM CERTEZA",
        "Created_at": "Sat Oct 26 17:42:32 +0000 2024"
    },
    {
        "User": "Irineu Negrão",
        "Content": "@mariadorosario É louca e surtada! PA não merece mais essa tragédia 🤣🤣🤣🤣🤣",
        "Created_at": "Sat Oct 26 17:43:12 +0000 2024"
    }
]