[
    {
        "User": "arnaud",
        "Content": "@mariadorosario essa semana vamos colocar o povão nas ruas e rumo a vitória",
        "Created_at": "Sun Oct 20 22:36:55 +0000 2024"
    },
    {
        "User": "Eder Rodrigo Felix",
        "Content": "@mariadorosario Vai virar sim confia 🤡",
        "Created_at": "Sun Oct 20 22:38:40 +0000 2024"
    },
    {
        "User": "Luiz tigre",
        "Content": "@mariadorosario Sai fora Muié ...",
        "Created_at": "Sun Oct 20 22:39:06 +0000 2024"
    },
    {
        "User": "Marcelo",
        "Content": "@mariadorosario Infelizmente eu não posso mostrar aqui o que tu vai ganhar kkkkkkk",
        "Created_at": "Sun Oct 20 22:41:17 +0000 2024"
    },
    {
        "User": "Verdecaco",
        "Content": "@mariadorosario @LulaOficial kkkk Isso é prá pedir uma reforma no banheiro que vai custar uns 3 milhões...",
        "Created_at": "Sun Oct 20 22:43:41 +0000 2024"
    },
    {
        "User": "Pobre",
        "Content": "@splucasaugusto Acho q pra @mariadorosario a policia consegue q prender bandido sem precisar da um tiro!🤦",
        "Created_at": "Sun Oct 20 22:47:50 +0000 2024"
    },
    {
        "User": "DEUS_OFICIAL",
        "Content": "@mariadorosario Vamos furar a bolha!\nDeixe seu like, comente e compartilhe nos seus grupos de WhatsApp e telegram!\n\nVote na mudança!\nVote certo!\nNo dia 27 \nVOTE MARIA 13\nSem medo de ser feliz!\nAperte o 13\nE confirme! ✅\n\n#MariaÉ13\n#ViraVotoPraMaria\n#Vote13\n#LulaBrasilSoberano",
        "Created_at": "Sun Oct 20 22:48:09 +0000 2024"
    },
    {
        "User": "DEUS_OFICIAL",
        "Content": "@mariadorosario Vamos furar a bolha!\nDeixe seu like, comente e compartilhe nos seus grupos de WhatsApp e telegram!\n\nVote na mudança!\nVote certo!\nNo dia 27 \nVOTE MARIA 13\nSem medo de ser feliz!\nAperte o 13\nE confirme! ✅\n\n#MariaÉ13\n#ViraVotoPraMaria\n#Vote13\n#LulaBrasilSoberano",
        "Created_at": "Sun Oct 20 22:49:22 +0000 2024"
    },
    {
        "User": "Josué Mendes",
        "Content": "@mariadorosario Domingo é dia de enterrar o PT de vez. Chorem, bobões!!!",
        "Created_at": "Sun Oct 20 22:50:19 +0000 2024"
    },
    {
        "User": "DEUS_OFICIAL",
        "Content": "@mariadorosario Vamos furar a bolha!\nDeixe seu like, comente e compartilhe nos seus grupos de WhatsApp e telegram!\n\nVote na mudança!\nVote certo!\nNo dia 27 \nVOTE MARIA 13\nSem medo de ser feliz!\nAperte o 13\nE confirme! ✅\n\n#MariaÉ13\n#ViraVotoPraMaria\n#Vote13\n#LulaBrasilSoberano https://t.co/WXDt1XMdNq",
        "Created_at": "Sun Oct 20 22:50:41 +0000 2024"
    },
    {
        "User": "Melo",
        "Content": "@mariadorosario @LulaOficial Acho incrível vcs falarem de união...",
        "Created_at": "Sun Oct 20 22:52:45 +0000 2024"
    },
    {
        "User": "DEUS_OFICIAL",
        "Content": "@mariadorosario Vamos furar a bolha!\nDeixe seu like, comente e compartilhe nos seus grupos de WhatsApp e telegram!\n\nVote na mudança!\nVote certo!\nNo dia 27 \nVOTE MARIA 13\nSem medo de ser feliz!\nAperte o 13\nE confirme! ✅\n\n#MariaÉ13\n#ViraVotoPraMaria\n#Vote13\n#LulaBrasilSoberano https://t.co/sIZzy7pRHe",
        "Created_at": "Sun Oct 20 22:52:48 +0000 2024"
    },
    {
        "User": "nelcioni lacerda Duart",
        "Content": "@Solangepossi @mariadorosario Parabéns 👏",
        "Created_at": "Sun Oct 20 22:52:56 +0000 2024"
    },
    {
        "User": "Mauro",
        "Content": "@mariadorosario Sai fora assombração",
        "Created_at": "Sun Oct 20 22:53:13 +0000 2024"
    },
    {
        "User": "DEUS_OFICIAL",
        "Content": "@mariadorosario Vamos furar a bolha!\nDeixe seu like, comente e compartilhe nos seus grupos de WhatsApp e telegram!\n\nVote na mudança!\nVote certo!\nNo dia 27 \nVOTE MARIA 13\nSem medo de ser feliz!\nAperte o 13\nE confirme! ✅\n\n#MariaÉ13\n#ViraVotoPraMaria\n#Vote13\n#LulaBrasilSoberano https://t.co/BRqvXKyHvv",
        "Created_at": "Sun Oct 20 22:53:55 +0000 2024"
    },
    {
        "User": "Josué Mendes",
        "Content": "@mariadorosario Domingo é dia de enterrar o PT de vez. Chorem, bobões!!!",
        "Created_at": "Sun Oct 20 22:55:15 +0000 2024"
    },
    {
        "User": "Maria do Rosário",
        "Content": "Uma Porto Alegre segura é aquela onde a chuva não signifique medo. \n\nA mudança segura deve ser por alguém que tenha compromisso com a segurança e a vida das pessoas. É Maria, vote 13!\n\n#MariaETamyres #MariaÉ13 #PovonaPrefeitura #PortoAlegre https://t.co/SxOd2xlTfu",
        "Created_at": "Sun Oct 20 22:57:55 +0000 2024"
    },
    {
        "User": "Maria do Rosário",
        "Content": "Uma Porto Alegre segura é aquela onde a chuva não signifique medo. \n\nA mudança segura deve ser por alguém que tenha compromisso com a segurança e a vida das pessoas. É Maria, vote 13!\n\n#MariaETamyres #MariaÉ13 #PovonaPrefeitura #PortoAlegre https://t.co/FYlxoY4wWh",
        "Created_at": "Sun Oct 20 22:58:01 +0000 2024"
    }
]