[
    {
        "User": "Jorge Fonseca.",
        "Content": "@alesilva_brasil @EderMauroPA @BrunoEnglerDM @andrefernm @carlosjordy Não seria melhor pedir para seus eleitores deixar o churrasco, o passeio, a pescaria, a praia, a viagem para outro dia que não fosse o dia das eleições e ir votar ?.",
        "Created_at": "Sat Oct 26 14:31:58 +0000 2024"
    },
    {
        "User": "Erick",
        "Content": "@iane_menezes @BrunoEnglerDM Hahahhahaa\nIgual a mamadeira de piroca e kit gay. Vcs são muito rasos",
        "Created_at": "Sat Oct 26 14:46:00 +0000 2024"
    },
    {
        "User": "Maurício Leszczyński",
        "Content": "Amanhã em BH é @BrunoEnglerDM 22! https://t.co/ci8wczeSJ9",
        "Created_at": "Sat Oct 26 14:50:38 +0000 2024"
    },
    {
        "User": "Maria Direita",
        "Content": "@BrunoEnglerDM @Ezequiasns DEUS PÁTRIA FAMÍLIA LIBERDADE 🇧🇷\n\nBRUNO ENGLER 2️⃣2️⃣\n#BrunoEngler #BrunoEngler22\n#BrunoEnglerParaPrefeito  #BrunoEnglerPrefeitoBeloHorizonte\n#BrunoEnglerPrefeito2024",
        "Created_at": "Sat Oct 26 14:53:39 +0000 2024"
    },
    {
        "User": "Rebel Alliance 🎧🎚🎶",
        "Content": "@itatiaia \"Onda\" de Direito de Resposta? Oh @itatiaia, vocês são uma rádio que informa com isenção ou são partidárias? Está mais que na cara que vocês apoiam a mentirada do @BrunoEnglerDM contra o @fuadnoman55 . Não sou eu quem disse, foi o Juiz que sentenciou. Isenção Itatiaia. Isenção.",
        "Created_at": "Sat Oct 26 14:54:55 +0000 2024"
    },
    {
        "User": "José Osmar Melo",
        "Content": "@_Janoninho @BolsonaroSP @BrunoEnglerDM @DamaresAlves @EduGiraoOficial @FlavioBolsonaro @GayerGus @abiliobrunini @coniboficial @CarolDeToni @Biakicis @congressoemfoco Gayer: cristão conservador e cidadão de bem,  né?  Vídeo de Suzano Startups! #TikTok https://t.co/i4bhZr4QzW",
        "Created_at": "Sat Oct 26 15:01:17 +0000 2024"
    },
    {
        "User": "JaneMM 💛🇧🇷💚",
        "Content": "@BrunoEnglerDM O povo quer renovar  e tirar esses políticos com cheiro de naftalina do poder. Esses políticos querem manter o sistema sujo da corrupção. Agora é #BrunoEngler22",
        "Created_at": "Sat Oct 26 15:06:51 +0000 2024"
    },
    {
        "User": "Elizabeth",
        "Content": "@lesmaaquatica @NewsLiberdade @nikolas_dm @BrunoEnglerDM Nikolas é um adolescente,  debocha dos gays, machista. Tem uma formação primitiva. Será que ele não é filho de militar?",
        "Created_at": "Sat Oct 26 15:16:50 +0000 2024"
    },
    {
        "User": "richardson valle",
        "Content": "@taoquei1 @RomeuZema Finalmente. No último dia, quando viu que o @BrunoEnglerDM JÁ ESTÁ ESLEITO. Muito bem vindo o apoio de última hora.",
        "Created_at": "Sat Oct 26 15:20:36 +0000 2024"
    },
    {
        "User": "A VERDADE SEMPRE TRIUNFA !!!!",
        "Content": "O tal Fuad que nenhum mineiro conhece é gago ou ficou gago com esta exposição?? @BrunoEnglerDM  #VoteBrunoEnglerPresidente",
        "Created_at": "Sat Oct 26 15:23:50 +0000 2024"
    },
    {
        "User": "Alexsandro Gariglio",
        "Content": "@BrunoEnglerDM VOTE 55\nAQUI EM BH MG APOIADOR DE BANDIDO LADRÃO DE JÓIA BOLSONARO NÃO SE CRIA",
        "Created_at": "Sat Oct 26 15:25:19 +0000 2024"
    },
    {
        "User": "Alexsandro Gariglio",
        "Content": "@BrunoEnglerDM VOTE 55\nAQUI EM BH MG APOIADOR DE BANDIDO LADRÃO DE JÓIA BOLSONARO NÃO SE CRIA",
        "Created_at": "Sat Oct 26 15:25:37 +0000 2024"
    },
    {
        "User": "X-Mick",
        "Content": "@nikolas_dm ATENÇÃO BH! É @BrunoEnglerDM SEM DÚVIDAS! DEPOIS, NÃO FALEM MAL DO RIO OU DE SÃO PAULO!",
        "Created_at": "Sat Oct 26 15:35:41 +0000 2024"
    },
    {
        "User": "mauriciotio389@gmail.com",
        "Content": "@BrunoEnglerDM meu   voto  amanhã   e   em   BRUNO  ENGLER",
        "Created_at": "Sat Oct 26 15:38:54 +0000 2024"
    },
    {
        "User": "Alexandre",
        "Content": "Que Senhor Deus possa dar a vitória para @andrefernm @EderMauroPA @BrunoEnglerDM e os demais que estão nessa batalha. Saibam que existem milhares de pessoas em jejum e oração por vocês.",
        "Created_at": "Sat Oct 26 15:53:55 +0000 2024"
    },
    {
        "User": "A VERDADE SEMPRE TRIUNFA !!!!",
        "Content": "@jairbolsonaro @BrunoEnglerDM @andrefernm @cristinagraeml @Lucassanchesp @FredRC @DepRosanaValle  Desenhado!!!! #EnDireitaBrasil",
        "Created_at": "Sat Oct 26 15:55:16 +0000 2024"
    }
]