[
    {
        "User": "Davidson 🐉$MON",
        "Content": "@taoquei1 @RomeuZema Já ia perder mais agora cavou a cova de vez kkkkk @fuadnoman55 neles!!!",
        "Created_at": "Fri Oct 25 11:09:06 +0000 2024"
    },
    {
        "User": "Fuad Noman 55",
        "Content": "Belo Horizonte não quer mentiras, brigas e extremismo. Nossa cidade vota em quem trabalha e cuida dela de verdade. Vamos continuar com as obras que transformam vidas e com políticas públicas que protegem as famílias, fazendo de BH um lugar cada vez melhor para viver. https://t.co/LJA7yT41Wy",
        "Created_at": "Fri Oct 25 11:26:36 +0000 2024"
    },
    {
        "User": "Fuad Noman 55",
        "Content": "Faltam 2 dias para votar 55!\n\nPropaganda Eleitoral – Fuad Noman, Prefeito/Álvaro Damião, Vice – Belo Horizonte/MG - Coligação BH Sempre em Frente – PSD – UNIÃO BRASIL – FEDERAÇÃO PSDB CIDADANIA - AVANTE – SOLIDARIEDADE – PRD - AGIR - PMB – CNPJ CANDIDATO 56.324.323/0001-95",
        "Created_at": "Fri Oct 25 11:32:02 +0000 2024"
    },
    {
        "User": "Xavier",
        "Content": "@em_com Cruzes. Estou com @fuadnoman55 . Esse gorrinho não passa credibilidade",
        "Created_at": "Fri Oct 25 12:01:49 +0000 2024"
    },
    {
        "User": "Isabela Penna Ceravolo",
        "Content": "É... uma única pista na principal avenida da cidade é realmente impraticável né @fuadnoman55 @BrunoEnglerDM https://t.co/0L1zg3zqdI",
        "Created_at": "Fri Oct 25 12:59:36 +0000 2024"
    },
    {
        "User": "Jackson Coelho",
        "Content": "@fuadnoman55 E o que tem a dizer sobre esse livro? https://t.co/mQfuXMNVME",
        "Created_at": "Fri Oct 25 13:07:10 +0000 2024"
    },
    {
        "User": "Sr João Infrouxável",
        "Content": "@Byanu Cobiça, do @fuadnoman55 13\n\nTem até relato de estupro infantil lá",
        "Created_at": "Fri Oct 25 13:23:13 +0000 2024"
    },
    {
        "User": "José Rodrigo",
        "Content": "@fuadnoman55 55 na cabeça domingo! Vamos dar um basta no fascismo!",
        "Created_at": "Fri Oct 25 13:52:05 +0000 2024"
    },
    {
        "User": "Branca Machado",
        "Content": "@fuadnoman55 Fuad 54. Escritor e prefeito 👏👏👏",
        "Created_at": "Fri Oct 25 14:00:56 +0000 2024"
    },
    {
        "User": "giani",
        "Content": "@RebelAliance13 @fuadnoman55 Esse livro fala de que? E pq foi vendido nas escolas p crianças? 🤨",
        "Created_at": "Fri Oct 25 14:15:59 +0000 2024"
    },
    {
        "User": "bagre",
        "Content": "@fuadnoman55 se vc trazer o my chemical romance pra bh tu ganha meu voto esse domingo",
        "Created_at": "Fri Oct 25 14:33:37 +0000 2024"
    },
    {
        "User": "Frida Gahlo",
        "Content": "@fuadnoman55 Uma escolha muito fácil: contra o negacionismo científico, o fundamentalismo, as fake news, a vagabundagem e o caô, bora de FUAD 55! Meu voto vai p um mineiro q trabalha a vida toda, ficha limpa, tem compromisso com a democracia e ainda AMA os livros. #Fuad55 BH quer ser feliz!",
        "Created_at": "Fri Oct 25 14:55:43 +0000 2024"
    },
    {
        "User": "batista",
        "Content": "@fuadnoman55 Prefeito Mary Kay  , metiras e sujeira e com esse prefeito mesmo  pede ao funcionários curti está postagem  , pior que existe na política está em BH  triste isso.",
        "Created_at": "Fri Oct 25 15:33:02 +0000 2024"
    },
    {
        "User": "HM",
        "Content": "@fuadnoman55 Quem acredita nessas pesquisas. Espero q o belo-horizontinos optem pela mudança. Que essa gestão pífia e atrasada de um fim. Hj pq caiu uns pingos d'água o transito não anda, sinal piscando em amarelo em toda cidade",
        "Created_at": "Fri Oct 25 16:14:46 +0000 2024"
    },
    {
        "User": "HM",
        "Content": "@fuadnoman55 Fiz ano passado um pedido de poda de árvore que tombou no Santo Antônio e que estava sendo segurada por uma placa de pare e nada.... a árvore precisou cair depois de 3 meses para fazerem algo",
        "Created_at": "Fri Oct 25 16:16:16 +0000 2024"
    },
    {
        "User": "Fuad Noman 55",
        "Content": "A verdade e o trabalho vencerão as fake news!\nFaltam 2 dias para apertar 55 e confirmar. Vamos juntos, sempre em frente! https://t.co/IfZCeN1csA",
        "Created_at": "Fri Oct 25 16:20:41 +0000 2024"
    },
    {
        "User": "Fuad Noman 55",
        "Content": "Propaganda Eleitoral – Fuad Noman, Prefeito/Álvaro Damião, Vice – Belo Horizonte/MG - Coligação BH Sempre em Frente – PSD – UNIÃO BRASIL – FEDERAÇÃO PSDB CIDADANIA - AVANTE – SOLIDARIEDADE – PRD - AGIR - PMB – CNPJ CANDIDATO 56.324.323/0001-95\n\n#prefeitofuad #FuadNoman55",
        "Created_at": "Fri Oct 25 16:20:42 +0000 2024"
    },
    {
        "User": "Rebel Alliance 🎧🎚🎶",
        "Content": "@sarahgiani_ @fuadnoman55 Não é vendido em escolas. Não é sugestão literária, muito menos pra crianças. É um livro de ficção.\n\nhttps://t.co/JVrJuj6sjz",
        "Created_at": "Fri Oct 25 16:26:54 +0000 2024"
    },
    {
        "User": "Rebel Alliance 🎧🎚🎶",
        "Content": "@sarahgiani_ @fuadnoman55 Se quiser aprender mais. Aprenda com a professora de literatura e não com politiqueiro barato.\n\nhttps://t.co/1ctXoucZTf",
        "Created_at": "Fri Oct 25 16:28:02 +0000 2024"
    }
]