[
    {
        "User": "DanielRossi_1910",
        "Content": "@GuilhermeBoulos igual Fidel fez em Cuba e Maduro em Caracas??",
        "Created_at": "Fri Oct 25 16:13:40 +0000 2024"
    },
    {
        "User": "aninha",
        "Content": "@GuilhermeBoulos nem o google acha esse safado",
        "Created_at": "Fri Oct 25 16:14:03 +0000 2024"
    },
    {
        "User": "Tgiott",
        "Content": "@GuilhermeBoulos Boné já ficou pronto! Em breve estará disponível para venda nas melhores lojas. https://t.co/e0bLoFQHUY",
        "Created_at": "Fri Oct 25 16:14:06 +0000 2024"
    },
    {
        "User": "Igor Costa",
        "Content": "@GuilhermeBoulos Cortaram sua propaganda hoje?",
        "Created_at": "Fri Oct 25 16:14:06 +0000 2024"
    },
    {
        "User": "Guilherme Boulos",
        "Content": "Quero seu voto no 50! https://t.co/85AHIn2BB6",
        "Created_at": "Fri Oct 25 16:14:08 +0000 2024"
    },
    {
        "User": "Guilherme Boulos",
        "Content": "#BoulosPrefeito50 • #MartaVice50 • Coligação #AmorporSaoPaulo • Federação PSOL - Rede, Federação Brasil da Esperança (PT - PCdoB - PV), PDT • CNPJ 56.233.510-0001/63",
        "Created_at": "Fri Oct 25 16:14:09 +0000 2024"
    },
    {
        "User": "Im free?",
        "Content": "@GuilhermeBoulos papis vc é luz te amamos",
        "Created_at": "Fri Oct 25 16:14:13 +0000 2024"
    },
    {
        "User": "V Vendetta🦑",
        "Content": "@GuilhermeBoulos Arriscado demais",
        "Created_at": "Fri Oct 25 16:14:17 +0000 2024"
    },
    {
        "User": "🇧🇷o ladrão🇧🇷não subiu🇧🇷a rampa🇧🇷",
        "Content": "@brealt @GuilhermeBoulos @pablomarcal Sabe quant9s eleit9res do ladra9 de banco vão votar no boulos??\n\nNenhum",
        "Created_at": "Fri Oct 25 16:14:17 +0000 2024"
    },
    {
        "User": "Klaus Fredo",
        "Content": "@samiabomfim @Glauber_Braga @GuilhermeBoulos Estes comunas apoiam isso. https://t.co/IlsQvTOyKs",
        "Created_at": "Fri Oct 25 16:14:33 +0000 2024"
    },
    {
        "User": "Silva",
        "Content": "@GuilhermeBoulos Eu voto é 50!",
        "Created_at": "Fri Oct 25 16:14:39 +0000 2024"
    },
    {
        "User": "pipa",
        "Content": "@ogabrielgg2 @GuilhermeBoulos como tá sendo?",
        "Created_at": "Fri Oct 25 16:14:42 +0000 2024"
    },
    {
        "User": "Tgiott",
        "Content": "@GuilhermeBoulos Parabéns Boulos https://t.co/WE0JSwYbl2",
        "Created_at": "Fri Oct 25 16:14:42 +0000 2024"
    },
    {
        "User": "Bruno Dias PARTID⚙️ DA CAUS🚩 OPERÁRIA",
        "Content": "@brealt @GuilhermeBoulos @pablomarcal Kkkkkkkkkkk\nEu diria que é acerto mesmo, Boulos e Pablo Marçal pra mim não estão tão distantes políticamente 😄",
        "Created_at": "Fri Oct 25 16:14:49 +0000 2024"
    },
    {
        "User": "ariana pequena",
        "Content": "@GuilhermeBoulos Parabéns Boulos, vc é um cara excepcional, ainda mais por aturar dialogar com essa marmota. Domingo é Boulos 50",
        "Created_at": "Fri Oct 25 16:14:55 +0000 2024"
    },
    {
        "User": "crislaine",
        "Content": "@GuilhermeBoulos Vc só aceitou pq tá precisando dos que votaram nele pra vc ganhar essa eleição( que vai ser muito difícil) se não vc nem iria ou seja tá desesperado",
        "Created_at": "Fri Oct 25 16:14:56 +0000 2024"
    },
    {
        "User": "LN",
        "Content": "@fsmcruz @GuilhermeBoulos todo mundo chamou o coach pro debate mesmo sem a exigência legal pra isso. Tudo pela audiência! Agora o Boulos, que tá atrás, faz uma jogada razoável pra quem tá atrás (se expor, aparecer, etc.) e isso vira um absurdo... Ridículo. Eles não se importam com + 4 anos de Nunes.",
        "Created_at": "Fri Oct 25 16:14:59 +0000 2024"
    }
]