[
    {
        "User": "Fabio rubro negroᶜʳᶠ Rio/ Florianópolis.",
        "Content": "@GuilhermeBoulos Uma chance pra foder a cidade. Igual seu patrão, está fodendo o país. Só maluco!",
        "Created_at": "Sat Oct 26 00:57:37 +0000 2024"
    },
    {
        "User": "federico riosa",
        "Content": "@GuilhermeBoulos Para ser Prefeito precisa ter algo que ainda falta-lhe.",
        "Created_at": "Sat Oct 26 00:57:39 +0000 2024"
    },
    {
        "User": "Diogo Cerqueira_",
        "Content": "@GuilhermeBoulos PSOL junto com o PT, boa coisa não é.",
        "Created_at": "Sat Oct 26 00:57:45 +0000 2024"
    },
    {
        "User": "Sol Santos",
        "Content": "@ptsaopaulosp \"A cidade que queremos promove a igualdade social com moradia digna e transporte público acessível. @GuilhermeBoulos\n@martasuplicy_\nGuilherme Boulos Prefeito  Marta Vice      Vote 50\n#Boulos50                      \n DOMINGO É BOULOS 50\n#LulaEstamosComVocê\"",
        "Created_at": "Sat Oct 26 00:57:45 +0000 2024"
    },
    {
        "User": "Sfreittas Freitas",
        "Content": "@GuilhermeBoulos A tá Boules 13! Aqueles quadrinhos pendurados na sua parede da sala? Não era um quadro de Jesus Cristo, mas sim de ditadores comunistas e assassinos.",
        "Created_at": "Sat Oct 26 00:57:51 +0000 2024"
    },
    {
        "User": "🚩Roberto Santos🚩🏴♥🎸SDV",
        "Content": "@GuilhermeBoulos @vinicios_betiol Parabéns Prefeito, foi muito bem !!!!",
        "Created_at": "Sat Oct 26 00:58:07 +0000 2024"
    },
    {
        "User": "lilibbar",
        "Content": "@_FelipeBelo @GuilhermeBoulos Pra começar, corrija, é raso!! \nE se vc é um filosofo da esquerda, só posso dizer, sinto muito!",
        "Created_at": "Sat Oct 26 00:58:53 +0000 2024"
    },
    {
        "User": "TEK",
        "Content": "@GuilhermeBoulos Acha que com ajuda de um fariseu farsante e como vc mesmo havia dito condenado vai ganhar mais voto?! Kkkk e achar que o povo é MUITO BURRO mesmo!",
        "Created_at": "Sat Oct 26 00:58:53 +0000 2024"
    },
    {
        "User": "Edmo",
        "Content": "@Como_Tanka @GuilhermeBoulos Isso, 13 e confirma!",
        "Created_at": "Sat Oct 26 00:58:54 +0000 2024"
    },
    {
        "User": "ⓟMarcelo D",
        "Content": "@schmittpaula @GuilhermeBoulos Nós lembramos, acho que quem não lembra, é ele.\nMais @schmittpaula Paulas, por favor!!!!!",
        "Created_at": "Sat Oct 26 00:59:02 +0000 2024"
    },
    {
        "User": "Gui Luuck",
        "Content": "@GuilhermeBoulos agora o Boules virou cristão KKKKKKKKKKKKKKKKKKKKK inacreditável",
        "Created_at": "Sat Oct 26 00:59:14 +0000 2024"
    },
    {
        "User": "Destro",
        "Content": "@GuilhermeBoulos A farinha.",
        "Created_at": "Sat Oct 26 00:59:33 +0000 2024"
    },
    {
        "User": "lilibbar",
        "Content": "@FABIOPEDROSA4 @GuilhermeBoulos E vc sofre de cegueira funcional.",
        "Created_at": "Sat Oct 26 00:59:46 +0000 2024"
    }
]