[
    {
        "User": "Douglas C. 🇾🇪",
        "Content": "@GuilhermeBoulos Ahahaha ….. político em época de eleição eh isso aí ….. kkkk",
        "Created_at": "Sat Oct 26 00:37:41 +0000 2024"
    },
    {
        "User": "Jones",
        "Content": "@GuilhermeBoulos Tem q estar muitos desconectado da realidade pra levar a sério um invasor igual esse 💩",
        "Created_at": "Sat Oct 26 00:37:45 +0000 2024"
    },
    {
        "User": "cr silva",
        "Content": "@pesquisas_elige @psol50 @GuilhermeBoulos Boulos prefeito 50",
        "Created_at": "Sat Oct 26 00:37:47 +0000 2024"
    },
    {
        "User": "Marcelo",
        "Content": "@GuilhermeBoulos Ahhhhh não kkkkkkkk",
        "Created_at": "Sat Oct 26 00:38:00 +0000 2024"
    },
    {
        "User": "Ana Paula",
        "Content": "@rodrigoluisvelo Marçal acabou apaixonado por @GuilhermeBoulos",
        "Created_at": "Sat Oct 26 00:38:10 +0000 2024"
    },
    {
        "User": "Rosely Loguercio",
        "Content": "@MaluNogueiraPT @parasamuel @InesNasciment12 @robeuman @WilmarPetista @borgescm @Cavalheira @Dry_ie @Mairaavelino64 @bethonira \"São Paulo só será justa com políticas que garantam educação, saúde e moradia digna para toda a população. @GuilhermeBoulos @martasuplicy_ Guilherme Boulos Prefeito  Marta Vice      Vote 50 #Boulos50                        DOMINGO É BOULOS 50 #LulaEstamosComVocê\" https://t.co/9Az3ICiuZu",
        "Created_at": "Sat Oct 26 00:38:43 +0000 2024"
    },
    {
        "User": "Claudio Otavio Vieira",
        "Content": "@GuilhermeBoulos BOULOS 50 O VOTO CONSCIENTE.",
        "Created_at": "Sat Oct 26 00:38:43 +0000 2024"
    },
    {
        "User": "Jones Selonke",
        "Content": "@GuilhermeBoulos Não gostei da ideia de vc  dar espaço para o Marçal, mas confesso que mandou muito bem, vc fez do limão uma saborosa limonada. Bora virar o jogo!  #Boulos50",
        "Created_at": "Sat Oct 26 00:38:51 +0000 2024"
    },
    {
        "User": "xp joao vlogs",
        "Content": "@milan_dark @GuilhermeBoulos Também pensei isso de início,mas o chefe não ia gostar de perder tantos clientes.",
        "Created_at": "Sat Oct 26 00:38:58 +0000 2024"
    },
    {
        "User": "cr silva",
        "Content": "@GiardiniNoronha @LulaOficial @GuilhermeBoulos Boulos prefeito 50",
        "Created_at": "Sat Oct 26 00:38:59 +0000 2024"
    },
    {
        "User": "relu",
        "Content": "@GuilhermeBoulos O Moacyr está animado pra cacete.",
        "Created_at": "Sat Oct 26 00:39:00 +0000 2024"
    },
    {
        "User": "Nilo Gustavo Rangel",
        "Content": "@GuilhermeBoulos Tá apelando né invasor.\nVc é UM SUJO INVASOR DE TERRAS.\nSeu mentor @LulaOficial já desviou verbas públicas pra sua campanha…..\nMalandragem é com o LULA.\nMas não vai levar não… \nInvasor.",
        "Created_at": "Sat Oct 26 00:39:17 +0000 2024"
    },
    {
        "User": "Fora Gentalha... #fodasssse",
        "Content": "@zeluizlhesdiz @GuilhermeBoulos E meu pai me escreveu que domingo vai de 50. Que alegria. Sou muito agradecida e mergulho com vocês e meu pai na luta. Minha dor é viver em Campinas.  Mas tô no movimento \"de virada\". Bora.",
        "Created_at": "Sat Oct 26 00:39:21 +0000 2024"
    },
    {
        "User": "RMP",
        "Content": "@ultrajano @GuilhermeBoulos Vai não... num vai não....rsrsrs",
        "Created_at": "Sat Oct 26 00:39:23 +0000 2024"
    },
    {
        "User": "cr silva",
        "Content": "@GuilhermeBoulos Boulos prefeito 50",
        "Created_at": "Sat Oct 26 00:39:41 +0000 2024"
    },
    {
        "User": "Gabriel Souza",
        "Content": "@yvonefcosta @matheustone22 @topiranath @GuilhermeBoulos Bolsonaro está sendo investigado, e eu não defendo Lula",
        "Created_at": "Sat Oct 26 00:39:48 +0000 2024"
    },
    {
        "User": "cr silva",
        "Content": "@GuilhermeBoulos Boulos prefeito 50",
        "Created_at": "Sat Oct 26 00:39:50 +0000 2024"
    },
    {
        "User": "LHAndrade50",
        "Content": "@fsmcruz @GuilhermeBoulos Como dizia minha avó\n\nO jogo só termina quando o juiz apita o final \n\nEu acredito",
        "Created_at": "Sat Oct 26 00:40:02 +0000 2024"
    }
]