[
    {
        "User": "🇧🇷 BOT Missão ⬛🟨⬜🐆",
        "Content": "@Amandavettorazz @GuilhermeBoulos Imagina o tanto de dejetos que são jogados diariamente nos mananciais por conta dessas ocupações",
        "Created_at": "Tue Oct 22 14:28:24 +0000 2024"
    },
    {
        "User": "katitamusical",
        "Content": "@Amandavettorazz @GuilhermeBoulos Mst não invade dona, mst OCUPA, se informe melhor, estude mais pra não pagar mico. Se ocupou é pq estava improdutiva. Pena que os paulistas votam mal pelo que vi agora,  mas boulos à de ganhar",
        "Created_at": "Tue Oct 22 14:28:52 +0000 2024"
    },
    {
        "User": "izabelamaral99@gmail.com",
        "Content": "@GuilhermeBoulos Deus te abençoe Boulos",
        "Created_at": "Tue Oct 22 14:28:54 +0000 2024"
    },
    {
        "User": "PIRAJANEVES",
        "Content": "@GuilhermeBoulos Kkkk tem cada coisa nesse mundo",
        "Created_at": "Tue Oct 22 14:29:25 +0000 2024"
    },
    {
        "User": "Juca1947!",
        "Content": "@GuilhermeBoulos INVASORES NÃO PASSARÃO!!!",
        "Created_at": "Tue Oct 22 14:29:38 +0000 2024"
    },
    {
        "User": "Cristiane Gomes",
        "Content": "@alexandreassiss @GuilhermeBoulos Ooo coitado tadinho  prefeito não será kkk",
        "Created_at": "Tue Oct 22 14:30:15 +0000 2024"
    },
    {
        "User": "Adãozinho",
        "Content": "No silencio, vamos virar essa eleição em #SaoPaulo manos e minas , bora todos juntos promover a mudança q a cidade de #SP tanto precisa .Vote #BoulosPrefeito50  @GuilhermeBoulos @martasuplicy_ @LulaOficial @JanjaLula @Anitta @felipeneto @VillaMarcovilla @marcosmion @xuxameneghel",
        "Created_at": "Tue Oct 22 14:30:23 +0000 2024"
    },
    {
        "User": "Whow Whow whow",
        "Content": "@GuilhermeBoulos O problema não é chegar de mãos vazias, e sim sair de mãos cheias da casa dos outro!",
        "Created_at": "Tue Oct 22 14:30:28 +0000 2024"
    },
    {
        "User": "Marcello Tibiriçá Muacad de Mulambo 😎🐵",
        "Content": "@capitalismodecu @devoltaomacaco @Reginatomasini @ferllenaf @GuilhermeBoulos O problema não é o Nunes, ele não se vende como “o bom, o justo, o impoluto, o anti sistema, a solução , o ético, o puro, o justo, o solucionador, o ficha limpa, etc..” boulos só não diz q é Jesus para não correr o risco de ser crucificado",
        "Created_at": "Tue Oct 22 14:30:38 +0000 2024"
    },
    {
        "User": "Beto Galvao",
        "Content": "@GuilhermeBoulos Boulos Jamais",
        "Created_at": "Tue Oct 22 14:31:09 +0000 2024"
    },
    {
        "User": "José SB",
        "Content": "@GuilhermeBoulos Só foi fazer propaganda política",
        "Created_at": "Tue Oct 22 14:32:39 +0000 2024"
    },
    {
        "User": "O Social",
        "Content": "@GuilhermeBoulos Chama a polícia! O casal teve a casa invadida e provavelmente foram feitos reféns... 🫨",
        "Created_at": "Tue Oct 22 14:33:37 +0000 2024"
    },
    {
        "User": "paulistaNãoFalaTu",
        "Content": "@julianopsol @GuilhermeBoulos A esquizofrenia é uma doença mental crônica que afeta a forma como uma pessoa pensa, sente e se comporta. Ela  se caracteriza por uma alteração cerebral que dificulta o discernimento  entre o que é real e o que é imaginário, o que é chamado de psicose.",
        "Created_at": "Tue Oct 22 14:34:07 +0000 2024"
    },
    {
        "User": "manu tg",
        "Content": "@GuilhermeBoulos Tô indo embora a mala já está lá fora vou te deixar.......",
        "Created_at": "Tue Oct 22 14:34:09 +0000 2024"
    },
    {
        "User": "Ronielton Alves de Oliveira",
        "Content": "@julia78805 @GuilhermeBoulos Pessoas normais tem amor aos seus filhos, e sofrem para dar o melhor a eles, diferente de politicos vagabundos que gastam milhões em campanha tudo por amor ao próximo né? Vão pro inferno hipócritas",
        "Created_at": "Tue Oct 22 14:34:12 +0000 2024"
    }
]