[
    {
        "User": "Sandro Alberto",
        "Content": "@randolfeap @GuilhermeBoulos Kkkkkkk... só que não!",
        "Created_at": "Fri Oct 25 23:38:07 +0000 2024"
    },
    {
        "User": "DiMMedeiros",
        "Content": "@GuilhermeBoulos Isso aí pessoal Domingo maceta o 13 nas urnas.",
        "Created_at": "Fri Oct 25 23:38:22 +0000 2024"
    },
    {
        "User": "Vera Egil🌹",
        "Content": "@GuilhermeBoulos Não se deixem enganar pelos malandros! BOULOS É,5️⃣0️⃣",
        "Created_at": "Fri Oct 25 23:38:34 +0000 2024"
    },
    {
        "User": "Leslye",
        "Content": "@GuilhermeBoulos Kkkkk conta outra, já sei \nVai dar picanha",
        "Created_at": "Fri Oct 25 23:38:43 +0000 2024"
    },
    {
        "User": "Breno Freire 1️⃣3️⃣ 🚩",
        "Content": "@GuilhermeBoulos BOULOS PREFEITO https://t.co/puOnxy610Q",
        "Created_at": "Fri Oct 25 23:38:44 +0000 2024"
    },
    {
        "User": "Barbosa",
        "Content": "@choquei Mano, o @GuilhermeBoulos foi na Live do Marçal que chamou ele de cheirador de cocaina…. Essa tia ai não tem nada não 👍 https://t.co/cx2s9tuRO3",
        "Created_at": "Fri Oct 25 23:38:45 +0000 2024"
    },
    {
        "User": "Sérgio Abreu",
        "Content": "@juhashistamm @GuilhermeBoulos Falei bem de boa, só uma constatação do que você falou no seu post... Se tiver tudo errado, ainda sim você vota no Lula. :)",
        "Created_at": "Fri Oct 25 23:39:03 +0000 2024"
    },
    {
        "User": "Marilu 🚩🚩☀️🍀",
        "Content": "Nem o Marçal resistiu ao charme do nosso prefeito @GuilhermeBoulos 💜5️⃣0️⃣💜 https://t.co/JrhbIZbfhm",
        "Created_at": "Fri Oct 25 23:39:03 +0000 2024"
    },
    {
        "User": "Breno Freire 1️⃣3️⃣ 🚩",
        "Content": "@GuilhermeBoulos DOMINGO É BOULOS 50 https://t.co/ikrSFCuRZX",
        "Created_at": "Fri Oct 25 23:39:09 +0000 2024"
    },
    {
        "User": "Sérgio Martinelli",
        "Content": "@GuilhermeBoulos Boulos, se Deus quiser alguém vai te dar um tiro 🙏",
        "Created_at": "Fri Oct 25 23:39:17 +0000 2024"
    },
    {
        "User": "bah*",
        "Content": "@RamosEneildes @LulaPTnosTrends @FazOLeSorria @AlexandrePT13CV @Alexand92840726 @CleuzaTur @borgescm @lacerdaeh @OAlagoas @Xavi93849835 @joaodomenech @Claudio75576514 @Baiantifascista @afonsocarlos @cacaubraga13 @Cricamg @EdsonFilho74 @Fernandcgr @helbarboza @Jonatha76186161 @lidiachaib @marcelochavee @menagildeth @opedeuta @Rene_sk8_ @silviamacedo00 @ValdirJesus15 @ALSSouza2 @BarrettoAlmeida @cezarchaves1 @didiindignada @emersonSVPT @gaosilva4 @itamar312 @juliocsribeiro @luizantoniosim9 @MariaEudaliaSa2 @NadiaMnccmoura @pintolima @RooseveltJuaz @supersonic99992 @wagnermereb @LulaOficial A transformação da cidade depende de mais justiça social e acesso à moradia para todos. \n@GuilhermeBoulos\n@martasuplicy_\nGuilherme Boulos Prefeito  Marta Vice      Vote 50\n#Boulos50           DOMINGO É BOULOS 50\n#LulaEstamosComVocê https://t.co/VURpqdm3q0",
        "Created_at": "Fri Oct 25 23:39:21 +0000 2024"
    },
    {
        "User": "Brasileiro Reacionário",
        "Content": "@GuilhermeBoulos Vc sabe que essa eleição é justamente para 2026?\nSe Boulos ganha, Lula vai ter força na cidade. Se Nunes ganha, Tarcísio sai fortalecido.",
        "Created_at": "Fri Oct 25 23:39:28 +0000 2024"
    },
    {
        "User": "Li reis",
        "Content": "@GuilhermeBoulos Todos vcs são iguais.",
        "Created_at": "Fri Oct 25 23:39:32 +0000 2024"
    },
    {
        "User": "Claudio Miron",
        "Content": "@GuilhermeBoulos Nossa que ridícula essa armação tudo amiguinho o comunista chamado de cheirador de pó e o ladrão do Marçal",
        "Created_at": "Fri Oct 25 23:39:35 +0000 2024"
    }
]