[
    {
        "User": "Daniel",
        "Content": "@samiabomfim @GuilhermeBoulos Muié feia da porra.\nDeixa de ser hipócrita Big Mac estragado.\nTodos nós sabemos que vocês são contra a vida,e que vocês são a favor da desgraça.",
        "Created_at": "Mon Oct 21 12:15:35 +0000 2024"
    },
    {
        "User": "Sandro.san",
        "Content": "@GuilhermeBoulos Cadê as feminista, deve tá contando o dinheiro pra ficar calada sobre a fala desse velho?? https://t.co/CevvFKME5R",
        "Created_at": "Mon Oct 21 12:15:47 +0000 2024"
    },
    {
        "User": "Danilo J Santos",
        "Content": "@SantosEdnyr @GuilhermeBoulos @martasuplicy_ Bom, se o povo Paulistano quer deixar a cidade como está largada sem prefeito q não assume suas irresponsabilidades, q joga a responsabilidade dele e da prefeitura nos outros, vota no Nunes.",
        "Created_at": "Mon Oct 21 12:16:02 +0000 2024"
    },
    {
        "User": "#ElusDomingues⏳",
        "Content": "@LiaDeSousa1 @GuilhermeBoulos Na \"Política\" nada mais importa...\nA não ser; os interesses daqueles que estão acima desse cargos \"Marionete\"\nEstamos andando em círculo 🛞",
        "Created_at": "Mon Oct 21 12:16:07 +0000 2024"
    },
    {
        "User": "de souza",
        "Content": "@samiabomfim @GuilhermeBoulos Ridícula mulher sem princípios sem carácter ninguém esqueceu o que vc fez e apoiou",
        "Created_at": "Mon Oct 21 12:16:13 +0000 2024"
    },
    {
        "User": "Cláudio F. P. Trindade",
        "Content": "@carlosgiannazi @GuilhermeBoulos 2 pais e uma mãe?",
        "Created_at": "Mon Oct 21 12:16:59 +0000 2024"
    },
    {
        "User": "Pronto, Falei!!",
        "Content": "@carlosgiannazi @GuilhermeBoulos A mãe do Lula nunca foi presa.",
        "Created_at": "Mon Oct 21 12:17:09 +0000 2024"
    },
    {
        "User": "Thiago Ferreira🐺",
        "Content": "@GuilhermeBoulos @martasuplicy_ BOULOS PREFEITO 50!",
        "Created_at": "Mon Oct 21 12:17:43 +0000 2024"
    },
    {
        "User": "RBdfwm",
        "Content": "@ColetivoSalaPT @monicabergamo @folha @GuilhermeBoulos Boulês + PT https://t.co/42tDXlS2p2",
        "Created_at": "Mon Oct 21 12:17:55 +0000 2024"
    },
    {
        "User": "Lene Carafini",
        "Content": "@LiaDeSousa1 @GuilhermeBoulos Que pena!",
        "Created_at": "Mon Oct 21 12:18:04 +0000 2024"
    },
    {
        "User": "Umbigo de Robô",
        "Content": "@GuilhermeBoulos @martasuplicy_ Ô, Boulos! O Ricardo Nunes confessou na cara dura, quando explicou como é a regulação da SABESP, pela Arsesp, que é a mesma responsável pela regulação da ANEEL, e você nem percebeu?\nFica a dica.\nPra cima deles!\n#Boulos50",
        "Created_at": "Mon Oct 21 12:19:00 +0000 2024"
    }
]